{
	"configurations" : 
	[
		{
			"directories" : 
			[
				{
					"build" : ".",
					"jsonFile" : "directory-.-Debug-f5ebdc15457944623624.json",
					"minimumCMakeVersion" : 
					{
						"string" : "3.28"
					},
					"projectIndex" : 0,
					"source" : ".",
					"targetIndexes" : 
					[
						0
					]
				}
			],
			"name" : "Debug",
			"projects" : 
			[
				{
					"directoryIndexes" : 
					[
						0
					],
					"name" : "Palindromes_",
					"targetIndexes" : 
					[
						0
					]
				}
			],
			"targets" : 
			[
				{
					"directoryIndex" : 0,
					"id" : "Palindromes_::@6890427a1f51a3e7e1df",
					"jsonFile" : "target-Palindromes_-Debug-8c01eca6cf84aeafa972.json",
					"name" : "Palindromes_",
					"projectIndex" : 0
				}
			]
		}
	],
	"kind" : "codemodel",
	"paths" : 
	{
		"build" : "/Users/zzy/Documents/GitHub/luo-lanqiao_do-problems/\u5b57\u7b26\u4e32-\u5165\u95e8/Palindromes-\u56de\u6587\u8bcd/cmake-build-debug",
		"source" : "/Users/zzy/Documents/GitHub/luo-lanqiao_do-problems/\u5b57\u7b26\u4e32-\u5165\u95e8/Palindromes-\u56de\u6587\u8bcd"
	},
	"version" : 
	{
		"major" : 2,
		"minor" : 6
	}
}
